tfwstartr/__init__.py
tfwstartr/config.py
tfwstartr/startr.py
tfwstartr/data/__init__.py
tfwstartr/data/languages.yaml
tfwstartr/data/npm.yaml
tfwstartr/data/pip.yaml
tfwstartr/utils/__init__.py
tfwstartr/utils/git_helper.py
tfwstartr/utils/package_manager/__init__.py
tfwstartr/utils/package_manager/package_manager.py
tfwstartr/utils/package_manager/strategies/__init__.py
tfwstartr/utils/package_manager/strategies/npm_strategy.py
tfwstartr/utils/package_manager/strategies/pip_strategy.py
tfwstartr/utils/package_manager/strategies/strategy_base.py
tfwstartr-1.0.3.dist-info/LICENSE
tfwstartr-1.0.3.dist-info/METADATA
tfwstartr-1.0.3.dist-info/WHEEL
tfwstartr-1.0.3.dist-info/top_level.txt
tfwstartr-1.0.3.dist-info/RECORD
