Metadata-Version: 2.1
Name: tfwstartr
Version: 1.0.3
Summary: Bootstrap TFW tutorials for the Avatao platform
Home-page: https://github.com/avatao-content/tfw-startr
Author: Avatao.com Innovative Learning Kft.
Author-email: support@avatao.com
License: Apache License 2.0
Platform: UNKNOWN
Classifier: Programming Language :: Python :: 3
Classifier: License :: OSI Approved :: Apache Software License
Classifier: Operating System :: OS Independent
Requires-Dist: requests (>=2.25.1)
Requires-Dist: GitPython (>=3.1.11)
Requires-Dist: PyYaml (>=5.3.1)
